nanosite/__init__.py
nanosite/build.py
nanosite/nanosite_tests.py
nanosite/packages.py
nanosite/server.py
nanosite/templates.py
nanosite/util.py
nanosite-0.1.13.dist-info/LICENSE.txt
nanosite-0.1.13.dist-info/METADATA
nanosite-0.1.13.dist-info/WHEEL
nanosite-0.1.13.dist-info/entry_points.txt
nanosite-0.1.13.dist-info/top_level.txt
nanosite-0.1.13.dist-info/RECORD
